monkey/__init__.py
monkey/crawler/__init__.py
monkey/crawler/crawlers/__init__.py
monkey/crawler/crawlers/zeep.py
monkey.crawler.soap-0.0.1.dev1.dist-info/LICENSE.txt
monkey.crawler.soap-0.0.1.dev1.dist-info/METADATA
monkey.crawler.soap-0.0.1.dev1.dist-info/WHEEL
monkey.crawler.soap-0.0.1.dev1.dist-info/top_level.txt
monkey.crawler.soap-0.0.1.dev1.dist-info/RECORD
